configs/Base-C2_L_R5021k_640b64_4x.yaml
configs/Base-DeformDETR_L_R50_4x.yaml
configs/Base_OVCOCO_C4_1x.yaml
configs/BoxSup-C2_LCOCO_CLIP_CXT21k_640b32_4x.yaml
configs/BoxSup-C2_LCOCO_CLIP_R18_640b32_4x.yaml
configs/BoxSup-C2_LCOCO_CLIP_R5021k_640b64_4x.yaml
configs/BoxSup-C2_LCOCO_CLIP_SwinB_896b32_4x.yaml
configs/BoxSup-C2_L_CLIP_R5021k_640b64_4x.yaml
configs/BoxSup-C2_L_CLIP_SwinB_896b32_4x.yaml
configs/BoxSup-C2_Lbase_CLIP_R5021k_640b64_4x.yaml
configs/BoxSup-C2_Lbase_CLIP_SwinB_896b32_4x.yaml
configs/BoxSup-DeformDETR_L_R50_2x.yaml
configs/BoxSup-DeformDETR_L_R50_4x.yaml
configs/BoxSup_OVCOCO_CLIP_R50_1x.yaml
configs/BoxSup_ViLD_200e.py
configs/Detic_DeformDETR_LI_R50_4x_ft4x.yaml
configs/Detic_LCOCOI21k_CLIP_CXT21k_640b32_4x_ft4x_max-size.yaml
configs/Detic_LCOCOI21k_CLIP_R18_640b32_4x_ft4x_max-size.yaml
configs/Detic_LCOCOI21k_CLIP_R5021k_640b32_4x_ft4x_max-size.yaml
configs/Detic_LCOCOI21k_CLIP_SwinB_896b32_4x_ft4x_max-size.yaml
configs/Detic_LI21k_CLIP_SwinB_896b32_4x_ft4x_max-size.yaml
configs/Detic_LI_CLIP_R5021k_640b64_4x_ft4x_max-size.yaml
configs/Detic_LI_CLIP_SwinB_896b32_4x_ft4x_max-size.yaml
configs/Detic_LbaseCCcapimg_CLIP_R5021k_640b64_4x_ft4x_max-size.yaml
configs/Detic_LbaseCCimg_CLIP_R5021k_640b64_4x_ft4x_max-size.yaml
configs/Detic_LbaseI_CLIP_R5021k_640b64_4x_ft4x_max-size.yaml
configs/Detic_LbaseI_CLIP_R5021k_640b64_4x_ft4x_predicted.yaml
configs/Detic_LbaseI_CLIP_SwinB_896b32_4x_ft4x_max-size.yaml
configs/Detic_OVCOCO_CLIP_R50_1x_caption.yaml
configs/Detic_OVCOCO_CLIP_R50_1x_max-size.yaml
configs/Detic_OVCOCO_CLIP_R50_1x_max-size_caption.yaml
configs/Detic_ViLD_200e.py
configs/__init__.py
datasets/__init__.py
datasets/metadata/Objects365_names_fix.csv
datasets/metadata/coco_clip_a+cname.npy
datasets/metadata/imagenet_lvis_wnid.txt
datasets/metadata/lvis_v1_clip_a+cname.npy
datasets/metadata/lvis_v1_train_cat_info.json
datasets/metadata/o365_clip_a+cnamefix.npy
datasets/metadata/oid_clip_a+cname.npy
detic/__init__.py
detic/config.py
detic_fork-0.0.5.dist-info/LICENSE
detic_fork-0.0.5.dist-info/METADATA
detic_fork-0.0.5.dist-info/WHEEL
detic_fork-0.0.5.dist-info/top_level.txt
detic_fork-0.0.5.dist-info/RECORD
